bootloader_flashing/__init__.py
bootloader_flashing/files/__init__.py
bootloader_flashing/files/hex.py
bootloader_flashing/files/s19.py
bootloader_flashing-0.1.3.dist-info/LICENSE
bootloader_flashing-0.1.3.dist-info/METADATA
bootloader_flashing-0.1.3.dist-info/WHEEL
bootloader_flashing-0.1.3.dist-info/top_level.txt
bootloader_flashing-0.1.3.dist-info/RECORD
