Metadata-Version: 2.1
Name: bootloader_flashing
Version: 0.1.3
Summary: utils for flashing bootloader
Home-page: https://github.com/my-python-utils/bootloader_flashing
License: MIT License
Requires-Python: >=3.11
License-File: LICENSE
